fastrtc/__init__.py
fastrtc/credentials.py
fastrtc/py.typed
fastrtc/reply_on_pause.py
fastrtc/reply_on_stopwords.py
fastrtc/stream.py
fastrtc/tracks.py
fastrtc/utils.py
fastrtc/webrtc.py
fastrtc/webrtc.pyi
fastrtc/webrtc_connection_mixin.py
fastrtc/websocket.py
fastrtc/pause_detection/__init__.py
fastrtc/pause_detection/protocol.py
fastrtc/pause_detection/silero.py
fastrtc/speech_to_text/__init__.py
fastrtc/speech_to_text/stt_.py
fastrtc/speech_to_text/test_file.wav
fastrtc/templates/component/_basePickBy-CzHZOPHw.js
fastrtc/templates/component/_baseUniq-DekjDzMJ.js
fastrtc/templates/component/arc-BU9PbiYH.js
fastrtc/templates/component/architectureDiagram-IEHRJDOE-CovdRaSi.js
fastrtc/templates/component/blockDiagram-JOT3LUYC-C4Gzx_5o.js
fastrtc/templates/component/c4Diagram-VJAJSXHY-ZJNRU26t.js
fastrtc/templates/component/channel-BqFrZsMU.js
fastrtc/templates/component/chunk-4BMEZGHF-DWVyb9R0.js
fastrtc/templates/component/chunk-A2AXSNBT-DjlSpw8Z.js
fastrtc/templates/component/chunk-AEK57VVT-BRfZc8yK.js
fastrtc/templates/component/chunk-D6G4REZN-Dqu3Ap2K.js
fastrtc/templates/component/chunk-RZ5BOZE2-DwZtji5F.js
fastrtc/templates/component/chunk-XZIHB7SX-ffDPNsxD.js
fastrtc/templates/component/classDiagram-GIVACNV2-DzSn_vPd.js
fastrtc/templates/component/classDiagram-v2-COTLJTTW-DzSn_vPd.js
fastrtc/templates/component/clone-RnTJuwI0.js
fastrtc/templates/component/cytoscape.esm-C2cgT2B2.js
fastrtc/templates/component/dagre-OKDRZEBW-D2UuWfNG.js
fastrtc/templates/component/diagram-SSKATNLV-D2IIG3bx.js
fastrtc/templates/component/diagram-VNBRO52H-4ehD3NmY.js
fastrtc/templates/component/erDiagram-Q7BY3M3F-Bb8_XrfD.js
fastrtc/templates/component/flowDiagram-4HSFHLVR-B54ZwAcW.js
fastrtc/templates/component/ganttDiagram-APWFNJXF-_Ggc9N9V.js
fastrtc/templates/component/gitGraphDiagram-7IBYFJ6S-qjZp0g2E.js
fastrtc/templates/component/graph-Dda6xMBk.js
fastrtc/templates/component/index-EQgvOkvr.js
fastrtc/templates/component/index.js
fastrtc-0.0.33.dist-info/METADATA
fastrtc-0.0.33.dist-info/WHEEL
fastrtc-0.0.33.dist-info/licenses/LICENSE
fastrtc-0.0.33.dist-info/RECORD
