Metadata-Version: 2.4
Name: fastrtc
Version: 0.0.33
Summary: The realtime communication library for Python
Project-URL: repository, https://github.com/gradio-app/fastrtc
Project-URL: issues, https://github.com/gradio-app/fastrtc/issues
Project-URL: Documentation, https://fastrtc.org/
Author-email: Freddy Boulton <arugula.ligand.92@icloud.com>
License-Expression: MIT
License-File: LICENSE
Keywords: audio,audio processing,computer vision,gradio-custom-component,image,machine learning,realtime,streaming,video,video processing,webrtc
Classifier: Development Status :: 3 - Alpha
Classifier: Operating System :: OS Independent
Classifier: Programming Language :: Python :: 3
Classifier: Programming Language :: Python :: 3 :: Only
Classifier: Programming Language :: Python :: 3.10
Classifier: Programming Language :: Python :: 3.11
Classifier: Programming Language :: Python :: 3.12
Classifier: Programming Language :: Python :: 3.13
Classifier: Topic :: Internet
Classifier: Topic :: Scientific/Engineering
Classifier: Topic :: Scientific/Engineering :: Artificial Intelligence
Classifier: Topic :: Scientific/Engineering :: Visualization
Classifier: Topic :: Software Development
Classifier: Topic :: Software Development :: Libraries
Classifier: Topic :: Software Development :: Libraries :: Application Frameworks
Classifier: Topic :: Software Development :: Libraries :: Python Modules
Requires-Python: >=3.10
Requires-Dist: aioice>=0.10.1
Requires-Dist: aiortc
Requires-Dist: audioop-lts; python_version >= '3.13'
Requires-Dist: gradio<6.0,>=4.0
Requires-Dist: librosa
Requires-Dist: numba>=0.60.0
Requires-Dist: numpy
Requires-Dist: standard-aifc; python_version >= '3.13'
Requires-Dist: standard-sunau; python_version >= '3.13'
Provides-Extra: dev
Requires-Dist: build; extra == 'dev'
Requires-Dist: httpx; extra == 'dev'
Requires-Dist: pytest; extra == 'dev'
Requires-Dist: pytest-asyncio; extra == 'dev'
Requires-Dist: twine; extra == 'dev'
Provides-Extra: stopword
Requires-Dist: fastrtc-moonshine-onnx; extra == 'stopword'
Requires-Dist: onnxruntime>=1.20.1; extra == 'stopword'
Provides-Extra: stt
Requires-Dist: fastrtc-moonshine-onnx; extra == 'stt'
Requires-Dist: onnxruntime>=1.20.1; extra == 'stt'
Provides-Extra: tts
Requires-Dist: kokoro-onnx; extra == 'tts'
Provides-Extra: vad
Requires-Dist: onnxruntime>=1.20.1; extra == 'vad'
